COPYING
MANIFEST.in
README.txt
requirements.txt
setup.py
bin/bootstrap_demo.sh
obdemo/__init__.py
obdemo/manage.py
obdemo/manage.sh
obdemo/models.py
obdemo/settings.py.in
obdemo/settings_background.py
obdemo/urls.py
obdemo/views.py
obdemo.egg-info/PKG-INFO
obdemo.egg-info/SOURCES.txt
obdemo.egg-info/dependency_links.txt
obdemo.egg-info/entry_points.txt
obdemo.egg-info/requires.txt
obdemo.egg-info/top_level.txt
obdemo/etc/sample_crontab
obdemo/management/__init__.py
obdemo/management/commands/__init__.py
obdemo/management/commands/import_boston_blocks.py
obdemo/management/commands/import_boston_hoods.py
obdemo/management/commands/import_boston_meetups.py
obdemo/management/commands/import_boston_news.py
obdemo/management/commands/import_boston_restaurants.py
obdemo/management/commands/import_boston_zips.py
obdemo/media/map_icons/README.txt
obdemo/media/map_icons/bar_coktail.gif
obdemo/media/map_icons/bar_coktail.png
obdemo/media/map_icons/calendar-3.png
obdemo/media/map_icons/caution.png
obdemo/media/map_icons/cinema.gif
obdemo/media/map_icons/cinema.png
obdemo/media/map_icons/congress.gif
obdemo/media/map_icons/congress.png
obdemo/media/map_icons/contract.gif
obdemo/media/map_icons/contract.png
obdemo/media/map_icons/conveniencestore.gif
obdemo/media/map_icons/conveniencestore.png
obdemo/media/map_icons/factory.gif
obdemo/media/map_icons/factory.png
obdemo/media/map_icons/fire.gif
obdemo/media/map_icons/fire.png
obdemo/media/map_icons/meetup.png
obdemo/media/map_icons/meetup.xcf
obdemo/media/map_icons/museum_art.gif
obdemo/media/map_icons/museum_art.png
obdemo/media/map_icons/newsagent.png
obdemo/media/map_icons/photo.gif
obdemo/media/map_icons/photo.png
obdemo/media/map_icons/police.gif
obdemo/media/map_icons/police.png
obdemo/media/map_icons/postal.png
obdemo/media/map_icons/regroup.png
obdemo/media/map_icons/restaurant.gif
obdemo/media/map_icons/restaurant.png
obdemo/media/map_icons/workoffice.gif
obdemo/media/map_icons/workoffice.png
obdemo/migrations/0001_initial.py
obdemo/migrations/0002_noop.py
obdemo/migrations/0003_load_demo_schemas.py
obdemo/migrations/0004_load_more_schemas.py
obdemo/migrations/0005_load_flickr_schema.py
