Metadata-Version: 1.0
Name: obdemo
Version: 1.2
Summary: Demo website configuration for OpenBlock (hyperlocal news for Django)
Home-page: http://openblockproject.org/docs
Author: Paul Winkler (for OpenPlans)
Author-email: ebcode@groups.google.com
License: GPLv3
Keywords: openblock
Platform: UNKNOWN
Classifier: Development Status :: 5 - Production/Stable
Classifier: Environment :: Web Environment
Classifier: Framework :: Django
Classifier: License :: OSI Approved :: GNU General Public License (GPL)
Classifier: Programming Language :: Python :: 2
Classifier: Operating System :: POSIX
Classifier: Topic :: Internet :: WWW/HTTP :: Dynamic Content :: News/Diary
Classifier: Topic :: Internet :: WWW/HTTP :: Indexing/Search
